mime_parser/__init__.py
mime_parser/__main__.py
mime_parser/arguments.py
mime_parser/entrypoint.py
mime_parser/favorite.py
mime_parser/global_register.py
mime_parser/variables.py
mime_parser/apps/__init__.py
mime_parser/apps/decode_main.py
mime_parser/apps/encode_main.py
mime_parser/apps/iana_main.py
mime_parser/apps/list_main.py
mime_parser/codec/__init__.py
mime_parser/codec/application/__init__.py
mime_parser/codec/application/gzip.py
mime_parser/codec/application/json.py
mime_parser/driver/__init__.py
mime_parser/driver/json.py
mime_parser/iana/__init__.py
mime_parser/iana/application.csv
mime_parser/iana/audio.csv
mime_parser/iana/font.csv
mime_parser/iana/image.csv
mime_parser/iana/message.csv
mime_parser/iana/model.csv
mime_parser/iana/multipart.csv
mime_parser/iana/registered_mime_types.py
mime_parser/iana/text.csv
mime_parser/iana/video.csv
mime_parser/logging/__init__.py
mime_parser/logging/loggers.py
mime_parser/logging/logging.py
mime_parser/mime/__init__.py
mime_parser/mime/mime_codec.py
mime_parser/mime/mime_codec_register.py
mime_parser/mime/mime_type.py
mime_parser/package/__init__.py
mime_parser/package/filter.py
mime_parser/pattern/__init__.py
mime_parser/pattern/singleton.py
mime_parser/plugin/__init__.py
mime_parser/plugin/find_plugin_codecs.py
mime_parser/regex/__init__.py
mime_parser/regex/access_filter.py
mime_parser/system/__init__.py
mime_parser/system/environment.py
mime_parser/system/environment_context.py
mime_parser/types/__init__.py
mime_parser/types/string/__init__.py
mime_parser/types/string/to_boolean.py
mime_parser-1.2.0.dist-info/LICENSE
mime_parser-1.2.0.dist-info/METADATA
mime_parser-1.2.0.dist-info/WHEEL
mime_parser-1.2.0.dist-info/entry_points.txt
mime_parser-1.2.0.dist-info/top_level.txt
mime_parser-1.2.0.dist-info/RECORD
