Metadata-Version: 2.1
Name: mime-parser
Version: 1.2.0
Summary: Encodes and decodes MIME data
Home-page: https://github.com/zer0/mime-parser
Author: zer0
Author-email: osom8979@gmail.com
Maintainer: zer0
Maintainer-email: osom8979@gmail.com
License: MIT License
Project-URL: GitHub: issues, https://github.com/zer0/mime-parser/issues
Project-URL: GitHub: repo, https://github.com/zer0/mime-parser
Platform: UNKNOWN
Classifier: Development Status :: 4 - Beta
Classifier: Framework :: AsyncIO
Classifier: Intended Audience :: Developers
Classifier: Operating System :: OS Independent
Classifier: Programming Language :: Python
Classifier: Programming Language :: Python :: 3.8
Classifier: Programming Language :: Python :: 3.9
Classifier: Programming Language :: Python :: 3.10
Classifier: Topic :: Software Development
Classifier: Topic :: Utilities
Classifier: License :: OSI Approved :: MIT License
Requires-Python: >=3.8
License-File: LICENSE
Provides-Extra: full
Requires-Dist: orjson (>=3.7.5) ; extra == 'full'
